getting_and_setting/__init__.py
getting_and_setting/mi_api.py
getting_and_setting/mi_cli.py
getting_and_setting/mi_constructor.py
getting_and_setting/mi_endpoints.py
getting_and_setting/mi_models.py
getting_and_setting/mi_outputs.py
getting_and_setting/mi_parser.py
getting_and_setting/mi_request.py
getting_and_setting-0.5.6.dist-info/entry_points.txt
getting_and_setting-0.5.6.dist-info/WHEEL
getting_and_setting-0.5.6.dist-info/METADATA
getting_and_setting-0.5.6.dist-info/RECORD
