Metadata-Version: 2.1
Name: getting-and-setting
Version: 0.5.6
Summary: An interface to interact with the Ion Mi Api.
License: GPL3.0
Author: Kim Timothy Engh
Author-email: kimothy@users.noreply.github.com
Requires-Python: >=3.9,<4.0
Classifier: License :: Other/Proprietary License
Classifier: Programming Language :: Python :: 3
Classifier: Programming Language :: Python :: 3.10
Classifier: Programming Language :: Python :: 3.9
Requires-Dist: keyring (>=23.5.1,<24.0.0)
Requires-Dist: requests (>=2.27.1,<3.0.0)
Requires-Dist: tabulate (>=0.8.9,<0.9.0)
Requires-Dist: typer (>=0.4.1,<0.5.0)
